frcm/__init__.py
frcm/datamodel/__init__.py
frcm/datamodel/model.py
frcm/datamodel/utils.py
frcm/fireriskmodel/__init__.py
frcm/fireriskmodel/compute.py
frcm/fireriskmodel/parameters.py
frcm/fireriskmodel/preprocess.py
frcm/fireriskmodel/utils.py
frcm/frcapi.py
frcm/weatherdata/__init__.py
frcm/weatherdata/client.py
frcm/weatherdata/client_met.py
frcm/weatherdata/extractor.py
frcm/weatherdata/extractor_met.py
frcm/weatherdata/utils.py
dynamic_frcm-1.0.2.dist-info/METADATA
dynamic_frcm-1.0.2.dist-info/WHEEL
dynamic_frcm-1.0.2.dist-info/licenses/COPYING.txt
dynamic_frcm-1.0.2.dist-info/RECORD
