Metadata-Version: 2.4
Name: dynamic-frcm
Version: 1.0.2
Summary: DYNAMIC fire risk computational model
License: LGPL-3.0-only
License-File: COPYING.txt
Author: Lars Michael Kristensen
Requires-Python: >=3.11,<4.0
Classifier: License :: OSI Approved :: GNU Lesser General Public License v3 (LGPLv3)
Classifier: Programming Language :: Python :: 3
Classifier: Programming Language :: Python :: 3.11
Classifier: Programming Language :: Python :: 3.12
Classifier: Programming Language :: Python :: 3.13
Classifier: Programming Language :: Python :: 3.14
Requires-Dist: numpy (>=2.0.0,<3.0.0)
Requires-Dist: pydantic (>=2.5.3,<3.0.0)
Requires-Dist: pytest (>=7.4.4,<8.0.0)
Requires-Dist: python-dateutil (>=2.8.2,<3.0.0)
Requires-Dist: python-decouple (>=3.8,<4.0)
Requires-Dist: requests (>=2.31.0,<3.0.0)
